scrahot/__init__.py
scrahot/app.py
scrahot/block_domain_extension.crx
scrahot/block_domain_extension.pem
scrahot/block_domain_extension.zip
scrahot/chromedriver
scrahot/items.py
scrahot/middlewares.py
scrahot/pipelines.py
scrahot/proxy_interceptor.py
scrahot/settings.py
scrahot/standard_json.py
scrahot/utils.py
scrahot/spiders/__init__.py
scrahot/spiders/base.py
scrahot/spiders/bestday.py
scrahot/spiders/booking.py
scrahot/spiders/cvc.py
scrahot/spiders/decolar.py
scrahot/spiders/despegar.py
scrahot/spiders/expedia.py
scrahot/spiders/hardrock.py
scrahot/spiders/hoteles.py
scrahot/spiders/hyatt.py
scrahot/spiders/palladium.py
scrahot/spiders/pumpfun.py
scrahot/spiders/test.py
scrahot-1.48.5.dist-info/METADATA
scrahot-1.48.5.dist-info/WHEEL
scrahot-1.48.5.dist-info/entry_points.txt
scrahot-1.48.5.dist-info/top_level.txt
scrahot-1.48.5.dist-info/RECORD
